ultraviolet/__init__.py
ultraviolet-0.0.0.dist-info/METADATA
ultraviolet-0.0.0.dist-info/WHEEL
ultraviolet-0.0.0.dist-info/RECORD
